<stl:stl xmlns:stl="http://developer.opentext.com/schemas/storyteller/layout" version="0.1">
  <stl:style>
    .text1 {
      border: 1px solid #000000
    }
    .span1 {
      font-family: Lato;
      font-size: 10pt
    }
    .table1 {
      border: 0.001in solid #000000;
      display: table
    }
    .row1 {
      -stl-shape-resize: free 0pt max 0pt max
    }
    .p1 {
      text-align: center
    }
  </stl:style>
  <stl:document>
    <stl:page w="3.6in" h="2.5in">
      <stl:text x="1in" y="0.5in" w="1in" h="0.198in" class="text1">
        <stl:story>
          <stl:p><stl:span class="span1">Hello</stl:span></stl:p>
        </stl:story>
      </stl:text>
      <stl:image x="0.4in" y="1in" w="2.715in" h="0.5in" src="wd:/cas/Y3hyOi8_aWQ9Y2ZlMDkwN2UtZWFlMi00ZDlkLWFkNzQtYjUzYTA2ODAwYzliO3Y9MTt0PTdjNjk4ZTFlLTdhMDUtZjA5Ny00NTYwLTdjYTc0ZWIyOGZhYw=="/>
      <stl:table x="0.6in" y="2in" class="table1">
        <stl:story>
          <stl:row h="0.25in" class="row1">
            <stl:cell w="1in">
              <stl:p class="p1"><stl:span class="span1">Open</stl:span></stl:p>
            </stl:cell>
            <stl:cell w="1in">
              <stl:p class="p1"><stl:span class="span1">text</stl:span></stl:p>
            </stl:cell>
          </stl:row>
        </stl:story>
      </stl:table>
    </stl:page>
  </stl:document>
</stl:stl>